alis/build/client/__init__.py
alis/build/client/grpc.py
alis_build_client-0.0.4.dist-info/METADATA
alis_build_client-0.0.4.dist-info/WHEEL
alis_build_client-0.0.4.dist-info/RECORD
